README.md
setup.py
djangoxform.egg-info/PKG-INFO
djangoxform.egg-info/SOURCES.txt
djangoxform.egg-info/dependency_links.txt
djangoxform.egg-info/not-zip-safe
djangoxform.egg-info/requires.txt
djangoxform.egg-info/top_level.txt
xform/__init__.py
xform/admin.py
xform/apps.py
xform/enketo_views.py
xform/forms.py
xform/models.py
xform/openrosaresponse.py
xform/renderers.py
xform/safe_create_instance.py
xform/serializers.py
xform/tags.py
xform/tests.py
xform/urls.py
xform/utils.py
xform/views.py
xform/migrations/0001_initial.py
xform/migrations/0002_attachment.py
xform/migrations/0003_datadictionary.py
xform/migrations/0004_auto_20190506_2001.py
xform/migrations/__init__.py